<?xml version="1.0" encoding="UTF-8"?>
<archetype-descriptor
        xmlns="http://maven.apache.org/plugins/maven-archetype-plugin/archetype-descriptor/1.0.0"
        xmlns:xsi="http://www.w3.org/2001/XMLSchema-instance"
        xsi:schemaLocation="http://maven.apache.org/plugins/maven-archetype-plugin/archetype-descriptor/1.0.0 http://maven.apache.org/xsd/archetype-descriptor-1.0.0.xsd">

    <requiredProperties>

    </requiredProperties>

    <fileSets>

        <fileSet filtered="true" packaged="true">
            <directory>src/main/java</directory>
            <includes>
                <include>**/*.java</include>
            </includes>
        </fileSet>

        <fileSet filtered="true">
            <directory>src/main/resources</directory>
            <includes>
                <include>**</include>
            </includes>
            <excludes>
                <exclude>logback-spring.xml</exclude>
            </excludes>
        </fileSet>
        <fileSet filtered="false">
            <directory>src/main/resources</directory>
            <includes>
                <include>logback-spring.xml</include>
            </includes>
        </fileSet>
        <fileSet filtered="true" packaged="true">
            <directory>src/test/java</directory>
            <includes>
                <include>**/*.java</include>
            </includes>
        </fileSet>
        <fileSet filtered="true">
            <directory>src/test/resources</directory>
            <includes>
                <include>**</include>
            </includes>
        </fileSet>

        <fileSet filtered="false">
            <directory>bin</directory>
            <includes>
                <include>manage-lush-service.sh</include>
                <include>make-docker-image.sh</include>
            </includes>
        </fileSet>

        <fileSet filtered="true">
            <directory>bin</directory>
            <includes>
                <include>rt-env.sh</include>
            </includes>
        </fileSet>

        <fileSet>
            <directory>./</directory>
            <includes>
                <include>README.MD</include>
            </includes>
        </fileSet>
    </fileSets>
</archetype-descriptor>